PingPongTool/PingPongTool.py
PingPongTool/__init__.py
PingPongTool-1.0.0.dist-info/METADATA
PingPongTool-1.0.0.dist-info/WHEEL
PingPongTool-1.0.0.dist-info/top_level.txt
PingPongTool-1.0.0.dist-info/RECORD
