Metadata-Version: 2.1
Name: PingPongTool
Version: 1.0.0
Summary: 쉬운 핑퐁빌더 사용을 위한 모듈
Home-page: https://github.com/minibox724/PingPongTool
Author: Minibox
Author-email: minibox724@gmail.com
License: UNKNOWN
Platform: UNKNOWN
Requires-Dist: cython
Requires-Dist: aiohttp
